{
  "$schema": "https://developer.microsoft.com/json-schemas/fabric/item/report/definition/visualContainer/2.6.0/schema.json",
  "name": "8a264e67014cc245b0e5",
  "position": {
    "x": 985.252014271596,
    "y": 137.22172900718607,
    "z": 5000,
    "height": 146.82725003768908,
    "width": 201.7159416405635,
    "tabOrder": 4000
  },
  "visual": {
    "visualType": "cardVisual",
    "query": {
      "queryState": {
        "Data": {
          "projections": [
            {
              "field": {
                "Measure": {
                  "Expression": {
                    "SourceRef": {
                      "Entity": "credit_card_full_dataset"
                    }
                  },
                  "Property": "Active Cardholders"
                }
              },
              "queryRef": "credit_card_full_dataset.Active Cardholders",
              "nativeQueryRef": "Active Cardholders"
            }
          ]
        }
      },
      "sortDefinition": {
        "sort": [
          {
            "field": {
              "Measure": {
                "Expression": {
                  "SourceRef": {
                    "Entity": "credit_card_full_dataset"
                  }
                },
                "Property": "Active Cardholders"
              }
            },
            "direction": "Descending"
          }
        ],
        "isDefaultSort": true
      }
    },
    "objects": {
      "label": [
        {
          "properties": {
            "show": {
              "expr": {
                "Literal": {
                  "Value": "false"
                }
              }
            }
          },
          "selector": {
            "id": "default"
          }
        }
      ],
      "outline": [
        {
          "properties": {
            "show": {
              "expr": {
                "Literal": {
                  "Value": "false"
                }
              }
            }
          },
          "selector": {
            "id": "default"
          }
        }
      ]
    },
    "visualContainerObjects": {
      "visualHeader": [
        {
          "properties": {
            "show": {
              "expr": {
                "Literal": {
                  "Value": "true"
                }
              }
            }
          }
        }
      ],
      "border": [
        {
          "properties": {
            "show": {
              "expr": {
                "Literal": {
                  "Value": "false"
                }
              }
            }
          }
        }
      ]
    },
    "drillFilterOtherVisuals": true
  },
  "filterConfig": {
    "filters": [
      {
        "name": "5d5e9cdfe7cb78224029",
        "field": {
          "Measure": {
            "Expression": {
              "SourceRef": {
                "Entity": "credit_card_full_dataset"
              }
            },
            "Property": "Active Cardholders"
          }
        },
        "type": "Advanced"
      }
    ]
  }
}